{
	"name": "Send_Email_Alert",
	"properties": {
		"activities": [
			{
				"name": "WaitActivity",
				"type": "Wait",
				"dependsOn": [
					{
						"activity": "Copy data1",
						"dependencyConditions": [
							"Succeeded"
						]
					}
				],
				"userProperties": [],
				"typeProperties": {
					"waitTimeInSeconds": 10
				}
			},
			{
				"name": "SendEmail",
				"type": "WebActivity",
				"dependsOn": [
					{
						"activity": "Copy data1",
						"dependencyConditions": [
							"Failed"
						]
					}
				],
				"policy": {
					"timeout": "0.12:00:00",
					"retry": 0,
					"retryIntervalInSeconds": 30,
					"secureOutput": false,
					"secureInput": false
				},
				"userProperties": [],
				"typeProperties": {
					"url": "https://prod-01.centralindia.logic.azure.com:443/workflows/f596889575a344b999ec3b3ff015d948/triggers/manual/paths/invoke?api-version=2016-10-01&sp=%2Ftriggers%2Fmanual%2Frun&sv=1.0&sig=rBqaoU-FlRiltjh8_Ud0t9izUEYdN_WEeWkHs6KtY_w",
					"method": "POST",
					"body": {
						"value": "{\n    \"to\":\"Koushik.Rangarajan@elait.com\",\n    \"subject\":\"Regarding Pipeline Fail\",\n    \"email_body\":\"Hi, \",\n    \"pipelineName\":\"@{pipeline().Pipeline}\",\n    \"pipelineRunid\":\"@{pipeline().RunId}\",\n    \"dataFactoryname\":\"@{pipeline().DataFactory}\",\n    \"pipelineTriggerid\":\"@{pipeline().TriggerId}\"\n}",
						"type": "Expression"
					}
				}
			},
			{
				"name": "Copy data1",
				"type": "Copy",
				"dependsOn": [],
				"policy": {
					"timeout": "0.12:00:00",
					"retry": 0,
					"retryIntervalInSeconds": 30,
					"secureOutput": false,
					"secureInput": false
				},
				"userProperties": [],
				"typeProperties": {
					"source": {
						"type": "DelimitedTextSource",
						"storeSettings": {
							"type": "AzureBlobFSReadSettings",
							"recursive": true,
							"wildcardFolderPath": "heyAlert",
							"wildcardFileName": "*txt",
							"enablePartitionDiscovery": false
						},
						"formatSettings": {
							"type": "DelimitedTextReadSettings"
						}
					},
					"sink": {
						"type": "DelimitedTextSink",
						"storeSettings": {
							"type": "AzureBlobFSWriteSettings"
						},
						"formatSettings": {
							"type": "DelimitedTextWriteSettings",
							"quoteAllText": true,
							"fileExtension": ".txt"
						}
					},
					"enableStaging": false,
					"translator": {
						"type": "TabularTranslator",
						"typeConversion": true,
						"typeConversionSettings": {
							"allowDataTruncation": true,
							"treatBooleanAsNumber": false
						}
					}
				},
				"inputs": [
					{
						"referenceName": "source_email_alert",
						"type": "DatasetReference"
					}
				],
				"outputs": [
					{
						"referenceName": "Destination_Email",
						"type": "DatasetReference"
					}
				]
			}
		],
		"annotations": [],
		"lastPublishTime": "2022-11-09T07:08:44Z"
	},
	"type": "Microsoft.DataFactory/factories/pipelines"
}